{
  "encounter_id": "26097e57-92f1-43c0-be19-dce1dbe2b322",
  "patient_id": "demo-patient-heel-suspicion",
  "wound_id": "demo-wound-heel-suspicion",
  "demo_case_id": "heel-suspicion",
  "created_at": "2026-04-10T15:46:58.639Z",
  "updated_at": "2026-04-10T15:46:58.650Z",
  "upload": {
    "stored_name": "heel-suspicion.png",
    "original_name": "heel-suspicion.png",
    "mime_type": "image/png",
    "size": 0,
    "image_url": "/demo/heel-suspicion.png",
    "file_path": "/home/syed-naveed-mahmood/wounddoc/WoundDoc/public/demo/heel-suspicion.png",
    "source": "demo"
  },
  "capture_context": {
    "reference_visible": true,
    "reference_type": "ruler",
    "reference_length_cm": 2,
    "reference_length_px": 88,
    "pixels_per_cm": 44,
    "calibration_status": "manual_reference",
    "notes": "Demo calibration preset"
  },
  "risk_form": {
    "body_site": "Right heel",
    "mobility_limited": true,
    "moisture_issue": false,
    "nutrition_risk": true,
    "device_present": false,
    "previous_pressure_injury": true,
    "support_surface_in_use": true,
    "formal_risk_score": 10,
    "comments": "Bedbound patient. Heel protector briefly off during hygiene."
  },
  "analysis": {
    "meta": {
      "encounter_id": "26097e57-92f1-43c0-be19-dce1dbe2b322",
      "patient_id": "demo-patient-heel-suspicion",
      "wound_id": "demo-wound-heel-suspicion",
      "demo_mode": true,
      "model_name": "demo-deterministic-v1",
      "timestamp": "2026-04-10T15:46:58.414Z",
      "warnings": [
        "Demo classifier adapter in use."
      ]
    },
    "roi": {
      "found": true,
      "bbox": [
        327,
        270,
        640,
        496
      ],
      "mask_bbox": [
        327,
        270,
        640,
        496
      ],
      "quality_flags": [
        "low_contrast"
      ],
      "crop_url": "/api/files/uploads/26097e57-92f1-43c0-be19-dce1dbe2b322/roi-crop.png",
      "overlay_url": "/api/files/uploads/26097e57-92f1-43c0-be19-dce1dbe2b322/roi-overlay.png",
      "mask_url": "/api/files/uploads/26097e57-92f1-43c0-be19-dce1dbe2b322/roi-mask.png",
      "mask_area_px": 56328.56742058011,
      "perimeter_px": 1082.7297021313577,
      "major_axis_px": 770.2234309542939,
      "minor_axis_px": 556.2498161526286,
      "segmentation_method": "heuristic_mask_v1",
      "crop_dimensions": {
        "width": 635,
        "height": 450
      }
    },
    "classification": {
      "top_class": "pressure_injury",
      "top_probability": 0.7899999999999998,
      "pressure_injury_probability": 0.7899999999999998,
      "class_probabilities": {
        "pressure_injury": 0.7899999999999998,
        "diabetic_ulcer": 0.04999999999999999,
        "venous_ulcer": 0.039999999999999994,
        "surgical_wound": 0.029999999999999992,
        "intact_skin": 0.08999999999999998
      },
      "adapter_name": "demo-deterministic-v1"
    },
    "concern_output": {
      "label": "stage_suspicion",
      "confidence": "moderate",
      "confidence_text": "Pressure-injury probability is elevated and supported by the current risk context.",
      "note": "Possible superficial pressure-injury pattern. This is a non-diagnostic stage suspicion for clinician review.",
      "stage_suspicion": "possible early pressure-related change"
    },
    "risk_form": {
      "body_site": "Right heel",
      "mobility_limited": true,
      "moisture_issue": false,
      "nutrition_risk": true,
      "device_present": false,
      "previous_pressure_injury": true,
      "support_surface_in_use": true,
      "formal_risk_score": 10,
      "comments": "Bedbound patient. Heel protector briefly off during hygiene."
    },
    "wound_metrics": {
      "ai_estimated": {
        "area_px": 56329,
        "area_cm2": 29.1,
        "length_cm": 17.51,
        "width_cm": 12.64,
        "perimeter_cm": 24.61,
        "depth_cm": null,
        "shape_regularity_score": 60,
        "tissue_composition": {
          "granulation": 100,
          "slough": 0,
          "eschar": 0,
          "epithelial": 0
        },
        "periwound_findings": [
          "visible surrounding erythema signal",
          "sustained pressure risk from limited mobility",
          "history of recurrent breakdown",
          "periwound visibility limited"
        ],
        "exudate_estimate": "no obvious heavy drainage signal; manual confirmation required",
        "image_quality_score": 82,
        "measurement_confidence": "moderate",
        "severity_score": 76
      },
      "clinician_entered": {
        "area_px": null,
        "area_cm2": null,
        "length_cm": null,
        "width_cm": null,
        "perimeter_cm": null,
        "depth_cm": null,
        "shape_regularity_score": null,
        "tissue_composition": null,
        "periwound_findings": [],
        "exudate_estimate": null,
        "image_quality_score": null,
        "measurement_confidence": null,
        "severity_score": null
      },
      "depth_guidance": "Depth is not inferable from a single 2D mobile photo. Use clinician-entered depth or a validated calibrated workflow."
    },
    "prevention_checklist": [
      {
        "id": "reposition-and-offload",
        "title": "Reposition and offload",
        "description": "Confirm a turning or offloading plan and reduce sustained pressure at the reported site.",
        "rationale": "Triggered by mobility limitation, nutrition risk, prior pressure injury, support surface already in use, formal risk score 10.",
        "priority": "urgent",
        "status": "recommended",
        "selected": true,
        "clinician_note": ""
      },
      {
        "id": "nutrition-review",
        "title": "Nutrition review",
        "description": "Confirm intake status and consider dietitian review if clinically appropriate.",
        "rationale": "Nutrition risk was reported in the structured risk form.",
        "priority": "priority",
        "status": "recommended",
        "selected": true,
        "clinician_note": ""
      },
      {
        "id": "support-surface-optimization",
        "title": "Support surface optimization",
        "description": "Review mattress, heel protector, or seat support configuration for current risk level.",
        "rationale": "Escalated because risk remains moderate to high.",
        "priority": "priority",
        "status": "recommended",
        "selected": true,
        "clinician_note": ""
      },
      {
        "id": "focused-skin-review",
        "title": "Focused skin review",
        "description": "Reassess the site with bedside exam, size estimate, and surrounding skin inspection.",
        "rationale": "AI output suggests a pressure-related concern that still requires clinician confirmation.",
        "priority": "urgent",
        "status": "review",
        "selected": true,
        "clinician_note": ""
      },
      {
        "id": "retake-standardized-image-if-needed",
        "title": "Retake standardized image if needed",
        "description": "Repeat the photo with better lighting, focus, and distance if the current image is not sufficient for documentation.",
        "rationale": "Quality flags detected: low_contrast.",
        "priority": "routine",
        "status": "monitor",
        "selected": true,
        "clinician_note": ""
      },
      {
        "id": "document-clinician-review",
        "title": "Document clinician review",
        "description": "Confirm the note, checklist, and image interpretation before export.",
        "rationale": "WoundWatch is documentation support only and not an autonomous diagnostic tool.",
        "priority": "urgent",
        "status": "review",
        "selected": true,
        "clinician_note": ""
      }
    ],
    "structured_note": {
      "summary": "Bedside documentation support for Right heel. AI review suggested stage suspicion with moderate confidence. Pressure-injury concern probability 79%. Clinician review required.",
      "full_note": "Reason for review: bedside wound documentation support after image capture of Right heel. Wound location: Right heel. AI concern summary: AI review suggested stage suspicion with moderate confidence. Pressure-injury concern probability 79%. Top class pressure injury at 79%. Possible superficial pressure-injury pattern. This is a non-diagnostic stage suspicion for clinician review. Depth guidance: depth is not inferable from a single 2D mobile photo and remains clinician-entered unless a validated calibrated workflow is used. Risk context: high overall pressure-injury risk. Signals noted: mobility limitation, nutrition risk, prior pressure injury, support surface already in use, formal risk score 10. Prevention bundle drafted: reposition and offload; nutrition review; support surface optimization; focused skin review; retake standardized image if needed. Comments: Bedbound patient. Heel protector briefly off during hygiene. Clinician review required prior to final documentation. Documentation support only. Not for autonomous diagnosis.",
      "copilot_statement": "Documentation support only. Not for autonomous diagnosis."
    }
  },
  "review": {
    "note_text": "Reason for review: bedside wound documentation support after image capture of Right heel. Wound location: Right heel. AI concern summary: AI review suggested stage suspicion with moderate confidence. Pressure-injury concern probability 79%. Top class pressure injury at 79%. Possible superficial pressure-injury pattern. This is a non-diagnostic stage suspicion for clinician review. Depth guidance: depth is not inferable from a single 2D mobile photo and remains clinician-entered unless a validated calibrated workflow is used. Risk context: high overall pressure-injury risk. Signals noted: mobility limitation, nutrition risk, prior pressure injury, support surface already in use, formal risk score 10. Prevention bundle drafted: reposition and offload; nutrition review; support surface optimization; focused skin review; retake standardized image if needed. Comments: Bedbound patient. Heel protector briefly off during hygiene. Clinician review required prior to final documentation. Documentation support only. Not for autonomous diagnosis.",
    "checklist": [
      {
        "id": "reposition-and-offload",
        "title": "Reposition and offload",
        "description": "Confirm a turning or offloading plan and reduce sustained pressure at the reported site.",
        "rationale": "Triggered by mobility limitation, nutrition risk, prior pressure injury, support surface already in use, formal risk score 10.",
        "priority": "urgent",
        "status": "recommended",
        "selected": true,
        "clinician_note": ""
      },
      {
        "id": "nutrition-review",
        "title": "Nutrition review",
        "description": "Confirm intake status and consider dietitian review if clinically appropriate.",
        "rationale": "Nutrition risk was reported in the structured risk form.",
        "priority": "priority",
        "status": "recommended",
        "selected": true,
        "clinician_note": ""
      },
      {
        "id": "support-surface-optimization",
        "title": "Support surface optimization",
        "description": "Review mattress, heel protector, or seat support configuration for current risk level.",
        "rationale": "Escalated because risk remains moderate to high.",
        "priority": "priority",
        "status": "recommended",
        "selected": true,
        "clinician_note": ""
      },
      {
        "id": "focused-skin-review",
        "title": "Focused skin review",
        "description": "Reassess the site with bedside exam, size estimate, and surrounding skin inspection.",
        "rationale": "AI output suggests a pressure-related concern that still requires clinician confirmation.",
        "priority": "urgent",
        "status": "review",
        "selected": true,
        "clinician_note": ""
      },
      {
        "id": "retake-standardized-image-if-needed",
        "title": "Retake standardized image if needed",
        "description": "Repeat the photo with better lighting, focus, and distance if the current image is not sufficient for documentation.",
        "rationale": "Quality flags detected: low_contrast.",
        "priority": "routine",
        "status": "monitor",
        "selected": true,
        "clinician_note": ""
      },
      {
        "id": "document-clinician-review",
        "title": "Document clinician review",
        "description": "Confirm the note, checklist, and image interpretation before export.",
        "rationale": "WoundWatch is documentation support only and not an autonomous diagnostic tool.",
        "priority": "urgent",
        "status": "review",
        "selected": true,
        "clinician_note": ""
      }
    ],
    "clinician_acknowledged": false,
    "clinician_wound_assessment": {
      "area_px": null,
      "area_cm2": null,
      "length_cm": null,
      "width_cm": null,
      "perimeter_cm": null,
      "depth_cm": null,
      "shape_regularity_score": null,
      "tissue_composition": null,
      "periwound_findings": [],
      "exudate_estimate": null,
      "image_quality_score": null,
      "measurement_confidence": null,
      "severity_score": null
    }
  },
  "export_paths": {
    "json_path": "/home/syed-naveed-mahmood/wounddoc/WoundDoc/data/outputs/26097e57-92f1-43c0-be19-dce1dbe2b322.json",
    "note_path": "/home/syed-naveed-mahmood/wounddoc/WoundDoc/data/outputs/26097e57-92f1-43c0-be19-dce1dbe2b322.txt"
  }
}
